mavnative.cpython-39-darwin.so
pymavlink/CSVReader.py
pymavlink/DFReader.py
pymavlink/__init__.py
pymavlink/fgFDM.py
pymavlink/mavexpression.py
pymavlink/mavextra.py
pymavlink/mavparm.py
pymavlink/mavtestgen.py
pymavlink/mavutil.py
pymavlink/mavwp.py
pymavlink/quaternion.py
pymavlink/rotmat.py
pymavlink/dialects/__init__.py
pymavlink/dialects/v10/ASLUAV.py
pymavlink/dialects/v10/ASLUAV.xml
pymavlink/dialects/v10/AVSSUAS.py
pymavlink/dialects/v10/AVSSUAS.xml
pymavlink/dialects/v10/__init__.py
pymavlink/dialects/v10/all.py
pymavlink/dialects/v10/all.xml
pymavlink/dialects/v10/ardupilotmega.py
pymavlink/dialects/v10/ardupilotmega.xml
pymavlink/dialects/v10/common.py
pymavlink/dialects/v10/common.xml
pymavlink/dialects/v10/development.py
pymavlink/dialects/v10/development.xml
pymavlink/dialects/v10/icarous.py
pymavlink/dialects/v10/icarous.xml
pymavlink/dialects/v10/matrixpilot.py
pymavlink/dialects/v10/matrixpilot.xml
pymavlink/dialects/v10/minimal.py
pymavlink/dialects/v10/minimal.xml
pymavlink/dialects/v10/paparazzi.py
pymavlink/dialects/v10/paparazzi.xml
pymavlink/dialects/v10/python_array_test.py
pymavlink/dialects/v10/python_array_test.xml
pymavlink/dialects/v10/standard.py
pymavlink/dialects/v10/standard.xml
pymavlink/dialects/v10/storm32.py
pymavlink/dialects/v10/storm32.xml
pymavlink/dialects/v10/test.py
pymavlink/dialects/v10/test.xml
pymavlink/dialects/v10/uAvionix.py
pymavlink/dialects/v10/uAvionix.xml
pymavlink/dialects/v10/ualberta.py
pymavlink/dialects/v10/ualberta.xml
pymavlink/dialects/v20/ASLUAV.py
pymavlink/dialects/v20/ASLUAV.xml
pymavlink/dialects/v20/AVSSUAS.py
pymavlink/dialects/v20/AVSSUAS.xml
pymavlink/dialects/v20/__init__.py
pymavlink/dialects/v20/all.py
pymavlink/dialects/v20/all.xml
pymavlink/dialects/v20/ardupilotmega.py
pymavlink/dialects/v20/ardupilotmega.xml
pymavlink/dialects/v20/common.py
pymavlink/dialects/v20/common.xml
pymavlink/dialects/v20/development.py
pymavlink/dialects/v20/development.xml
pymavlink/dialects/v20/icarous.py
pymavlink_bir_k-2.4.25.dist-info/COPYING
pymavlink_bir_k-2.4.25.dist-info/METADATA
pymavlink_bir_k-2.4.25.dist-info/WHEEL
pymavlink_bir_k-2.4.25.dist-info/top_level.txt
pymavlink_bir_k-2.4.25.dist-info/RECORD
